ups_pi/__init__.py
ups_pi/__main__.py
ups_pi/cli.py
ups_pi/config.py
ups_pi/power_manager.py
ups_pi/service.py
ups_pi/ups_communication.py
ups_pi/ups_manager.py
ups_pi-2.0.1.dist-info/licenses/LICENSE
ups_pi-2.0.1.dist-info/METADATA
ups_pi-2.0.1.dist-info/WHEEL
ups_pi-2.0.1.dist-info/entry_points.txt
ups_pi-2.0.1.dist-info/top_level.txt
ups_pi-2.0.1.dist-info/RECORD
