Metadata-Version: 2.4
Name: ups-pi
Version: 2.0.1
Summary: uart-based ups power management for raspberry pi
Author-email: ethan <ethan@gtfo.dev>
License: MIT
Classifier: Development Status :: 5 - Production/Stable
Classifier: Intended Audience :: System Administrators
Classifier: License :: OSI Approved :: MIT License
Classifier: Operating System :: POSIX :: Linux
Classifier: Programming Language :: Python :: 3
Classifier: Programming Language :: Python :: 3.8
Classifier: Programming Language :: Python :: 3.9
Classifier: Programming Language :: Python :: 3.10
Classifier: Programming Language :: Python :: 3.11
Classifier: Topic :: System :: Hardware
Classifier: Topic :: System :: Power (UPS)
Requires-Python: >=3.8
License-File: LICENSE
Requires-Dist: pyserial>=3.5
Provides-Extra: gpio
Requires-Dist: RPi.GPIO>=0.7.0; extra == "gpio"
Provides-Extra: dev
Requires-Dist: pytest>=7.0.0; extra == "dev"
Requires-Dist: pytest-cov>=4.0.0; extra == "dev"
Requires-Dist: black>=23.0.0; extra == "dev"
Requires-Dist: flake8>=6.0.0; extra == "dev"
Requires-Dist: mypy>=1.0.0; extra == "dev"
Dynamic: license-file
